ha_mqtt_publisher/__init__.py
ha_mqtt_publisher/availability.py
ha_mqtt_publisher/commands.py
ha_mqtt_publisher/config.py
ha_mqtt_publisher/ha_discovery/__init__.py
ha_mqtt_publisher/ha_discovery/constants.py
ha_mqtt_publisher/ha_discovery/device.py
ha_mqtt_publisher/ha_discovery/discovery_manager.py
ha_mqtt_publisher/ha_discovery/enhanced_publisher.py
ha_mqtt_publisher/ha_discovery/entity.py
ha_mqtt_publisher/ha_discovery/publisher.py
ha_mqtt_publisher/ha_discovery/status_sensor.py
ha_mqtt_publisher/ha_mqtt_config/ha_mqtt_discovery.json.example
ha_mqtt_publisher/ha_mqtt_discovery/__init__.py
ha_mqtt_publisher/ha_mqtt_discovery/discovery.py
ha_mqtt_publisher/ha_mqtt_discovery/topic.py
ha_mqtt_publisher/json_publish.py
ha_mqtt_publisher/message_handler.py
ha_mqtt_publisher/mqtt_utils.py
ha_mqtt_publisher/publisher.py
ha_mqtt_publisher/service_runner.py
ha_mqtt_publisher/status.py
ha_mqtt_publisher/topic_map.py
ha_mqtt_publisher/validator.py
ha_mqtt_publisher-0.3.4.dist-info/LICENSE
ha_mqtt_publisher-0.3.4.dist-info/METADATA
ha_mqtt_publisher-0.3.4.dist-info/WHEEL
ha_mqtt_publisher-0.3.4.dist-info/RECORD
