Metadata-Version: 2.3
Name: ha-mqtt-publisher
Version: 0.3.4
Summary: An MQTT publisher package
License: MIT
Keywords: mqtt,publisher,iot
Author: ronschaeffer
Requires-Python: >=3.11
Classifier: License :: OSI Approved :: MIT License
Classifier: Programming Language :: Python :: 3
Classifier: Programming Language :: Python :: 3.11
Classifier: Programming Language :: Python :: 3.12
Classifier: Programming Language :: Python :: 3.13
Provides-Extra: dev
Requires-Dist: codespell (>=2.1.0) ; extra == "dev"
Requires-Dist: paho-mqtt (>=2.1.0)
Requires-Dist: pre-commit (>=4.2.0) ; extra == "dev"
Requires-Dist: pytest (>=8.3.4) ; extra == "dev"
Requires-Dist: pytest-cov (>=6.2.1) ; extra == "dev"
Requires-Dist: pytest-mock (>=3.10.0) ; extra == "dev"
Requires-Dist: python-dotenv (>=1.1.1)
Requires-Dist: pyyaml (>=6.0)
Requires-Dist: ruff (>=0.12.7) ; extra == "dev"
Requires-Dist: typing-extensions (>=4.7.0)
Project-URL: Homepage, https://github.com/ronschaeffer/ha_mqtt_publisher
Project-URL: Repository, https://github.com/ronschaeffer/ha_mqtt_publisher
